LICENSE
LONG_DESCRIPTION.rst
MANIFEST.in
README.md
VERSION
setup.cfg
setup.py
wia/__init__.py
wia/error.py
wia/resource.py
wia/rest_client.py
wia/stream_client.py
wia/util.py
wia/version.py
wia.egg-info/PKG-INFO
wia.egg-info/SOURCES.txt
wia.egg-info/dependency_links.txt
wia.egg-info/requires.txt
wia.egg-info/top_level.txt
wia/test/__init__.py
wia/test/test_stream.py
wia/test/resources/__init__.py
wia/test/resources/test_commands.py
wia/test/resources/test_events.py
wia/test/resources/test_init.py
wia/test/resources/test_locations.py
wia/test/resources/test_spaces.py