Metadata-Version: 1.2
Name: wia
Version: 1.1.0
Summary: This client library is designed to support the Wia APIs
Home-page: https://github.com/wiaio/wia-python-sdk
Author: Wia
Author-email: team@wia.io
Maintainer: Conall Laverty
Maintainer-email: team@wia.io
License: MIT
Platform: UNKNOWN
Classifier: License :: OSI Approved :: MIT License
Classifier: Programming Language :: Python
Classifier: Programming Language :: Python :: 2.6
Classifier: Programming Language :: Python :: 2.7
Classifier: Programming Language :: Python :: 3
Classifier: Programming Language :: Python :: 3.3
Classifier: Programming Language :: Python :: 3.4
Classifier: Programming Language :: Python :: 3.5
